{
    "product_id": "1220601",
    "url": "https://shopino.app/product/1220601",
    "main_category": "زنانه",
    "sub_category": "شلوارک زنانه",
    "title": "شلوارک زنانه Colin’s کد CL1068956",
    "description": "توضیحات\n\n  با احترام خدمت مشتریان گرامی:\n\nترجیحا شستشو به صورت خشکشویی انجام شود.\nشستشو با ماشین لباسشویی با حداکثر دمای ۳۰ درجه سانتیگراد\nبا کمترین زمان شستشوی ماشین و روی حالت شستشو با دست شسته شود.\nاتوکشی با حداکثر دمای 110 درجه سانتیگراد\nاز خشک کن استفاده نشود.\nاز تماس مواد سفید کننده با لباس اجتناب شود .\nاز چلاندن و کشیدن پارچه بپرهیزید.",
    "price": "716,000",
    "old_price": "1,790,000",
    "discount_percentage": "60 %",
    "shop_url": "https://shopino.app/shops/1727",
    "shop_name": "کی شاپ",
    "images": [
        "assets/زنانه/شلوارک زنانه/1220601/d5eb56ccba316f43c20a6ff5db3ac0ac.webp",
        "assets/زنانه/شلوارک زنانه/1220601/37f472f350d87b791ef8c2d0d3516e45.webp",
        "assets/زنانه/شلوارک زنانه/1220601/93904e855b14c2d9c136bf7a28808949.webp",
        "assets/زنانه/شلوارک زنانه/1220601/c68d5a8d45e566b87e6ab93d4e7b42c2.webp",
        "assets/زنانه/شلوارک زنانه/1220601/92c657e9357b5c210ae6d42ce12524c1.webp",
        "assets/زنانه/شلوارک زنانه/1220601/d5eb56ccba316f43c20a6ff5db3ac0ac.webp",
        "assets/زنانه/شلوارک زنانه/1220601/37f472f350d87b791ef8c2d0d3516e45.webp",
        "assets/زنانه/شلوارک زنانه/1220601/93904e855b14c2d9c136bf7a28808949.webp",
        "assets/زنانه/شلوارک زنانه/1220601/c68d5a8d45e566b87e6ab93d4e7b42c2.webp",
        "assets/زنانه/شلوارک زنانه/1220601/92c657e9357b5c210ae6d42ce12524c1.webp",
        "assets/زنانه/شلوارک زنانه/1220601/2849b021a15a16fd95b5b515411101ad.jpg",
        "assets/زنانه/شلوارک زنانه/1220601/2849b021a15a16fd95b5b515411101ad.jpg",
        "assets/زنانه/شلوارک زنانه/1220601/2849b021a15a16fd95b5b515411101ad.jpg"
    ],
    "related_lists": [
        {
            "name": "شلوار جین ARK زنانه"
        },
        {
            "name": "شلوارک چاک‌دار نخی زنانه"
        },
        {
            "name": "شلوارک بندی لنین زنانه"
        }
    ]
}