{
    "product_id": "668605",
    "url": "https://shopino.app/product/668605",
    "main_category": "زنانه",
    "sub_category": "اکسسوری مو زنانه",
    "title": "تل مو پارچه ای مدل پاپیون گره‌ای فانتزی طرح اسب تک شاخ یونیکورنی",
    "description": "تل مو پارچه ای مدل پاپیون گره ای فانتزی طرح اسب تک شاخ یونیکورنی\nدر دو رنگ زرد و سبز\nمناسب برای تمام سنین\nجنس پارچه ای",
    "price": "No Price",
    "old_price": null,
    "discount_percentage": null,
    "shop_url": "https://shopino.app/shops/1570",
    "shop_name": "سبد طلایی",
    "images": [
        "assets/زنانه/اکسسوری مو زنانه/668605/6cf5b66157a5daf23c09b51c6efbdc6c.jpg",
        "assets/زنانه/اکسسوری مو زنانه/668605/0272ac938a7401575653b01fde44ee45.jpg",
        "assets/زنانه/اکسسوری مو زنانه/668605/6cf5b66157a5daf23c09b51c6efbdc6c.jpg",
        "assets/زنانه/اکسسوری مو زنانه/668605/0272ac938a7401575653b01fde44ee45.jpg",
        "assets/زنانه/اکسسوری مو زنانه/668605/3f5208ef3d2c97c8ed5a62bca77c9268.webp",
        "assets/زنانه/اکسسوری مو زنانه/668605/3f5208ef3d2c97c8ed5a62bca77c9268.webp",
        "assets/زنانه/اکسسوری مو زنانه/668605/3f5208ef3d2c97c8ed5a62bca77c9268.webp"
    ],
    "related_lists": [
        {
            "name": "کلیپس شمعی مینی زنانه"
        },
        {
            "name": "پک گیره مستطیل زنانه"
        },
        {
            "name": "کش مو ساتن زنانه"
        }
    ]
}