{
    "product_id": "1367945",
    "url": "https://shopino.app/product/1367945",
    "main_category": "زنانه",
    "sub_category": "تاپ زنانه",
    "title": "تاپ زنانه بندی بنیتا اوت لت ناموجود",
    "description": "مدل تاپ : اسلیم فیت",
    "price": "No Price",
    "old_price": null,
    "discount_percentage": null,
    "shop_url": "https://shopino.app/shops/1610",
    "shop_name": "سیلکا",
    "images": [
        "assets/زنانه/تاپ زنانه/1367945/9b29e8c8c9ac920bfd5631c41980d60b.jpg",
        "assets/زنانه/تاپ زنانه/1367945/9b29e8c8c9ac920bfd5631c41980d60b.jpg",
        "assets/زنانه/تاپ زنانه/1367945/b50126cb59819e21e4d36eed887891ad.jpg",
        "assets/زنانه/تاپ زنانه/1367945/b50126cb59819e21e4d36eed887891ad.jpg",
        "assets/زنانه/تاپ زنانه/1367945/b50126cb59819e21e4d36eed887891ad.jpg"
    ],
    "related_lists": [
        {
            "name": "تاپ دکلته گل‌دار زنانه"
        },
        {
            "name": "نیم تنه حلقه ای سلین زنانه"
        },
        {
            "name": "نیم تنه دکلته پلیسه زنانه"
        }
    ]
}