{
    "product_id": "1110580",
    "url": "https://shopino.app/product/1110580",
    "main_category": "مردانه",
    "sub_category": "کمربند مردانه",
    "title": "کمربند چرم مصنوعی مردانه U5589azns U5589AZ21AU",
    "description": "این کمربند که از جنس چرم مانند با طرح سگک فلزی شیک ساخته شده است، می تواند با قطعاتی مانند کت و شلوارهای سبک کلاسیک، پیراهن و شلوار پارچه ای ترکیب شود. کمربند چرم مصنوعی مردانه DeFacto بخشی جدایی ناپذیر از شیک ترین ترکیبات شما خواهد بود و با طراحی ساده خود استفاده آسان را فراهم می کند.\nپلی اورتان 100%\nابعاد محصول: 3.5 سانتی متر\nرنگ: مشکی\nجزء مواد: 100% محصول\nدستورالعمل شستشو: نوع 4\nجنسیت: مرد\nبرند: Defacto",
    "price": "No Price",
    "old_price": null,
    "discount_percentage": null,
    "shop_url": "https://shopino.app/shops/1671",
    "shop_name": "ترندی‌تو",
    "images": [
        "assets/مردانه/کمربند مردانه/1110580/5a3408a5f08af3d99125dfb19e1c5be6.jpg",
        "assets/مردانه/کمربند مردانه/1110580/008fbced2f42f43b7733e6e5f01b4e70.jpg",
        "assets/مردانه/کمربند مردانه/1110580/077af42e3fee6bef9ab7784d1d7aaf09.jpg",
        "assets/مردانه/کمربند مردانه/1110580/81863a35a30d365b7922b389f7b467cc.jpg",
        "assets/مردانه/کمربند مردانه/1110580/5a3408a5f08af3d99125dfb19e1c5be6.jpg",
        "assets/مردانه/کمربند مردانه/1110580/008fbced2f42f43b7733e6e5f01b4e70.jpg",
        "assets/مردانه/کمربند مردانه/1110580/077af42e3fee6bef9ab7784d1d7aaf09.jpg",
        "assets/مردانه/کمربند مردانه/1110580/81863a35a30d365b7922b389f7b467cc.jpg",
        "assets/مردانه/کمربند مردانه/1110580/5bda2d22adb712edf035b4e3df734392.webp",
        "assets/مردانه/کمربند مردانه/1110580/5bda2d22adb712edf035b4e3df734392.webp",
        "assets/مردانه/کمربند مردانه/1110580/5bda2d22adb712edf035b4e3df734392.webp"
    ],
    "related_lists": [
        {
            "name": "کمربند مشکی PINGH مردانه"
        },
        {
            "name": "کمربند مردانه ذغالی"
        },
        {
            "name": "کمربند بندی مردانه"
        }
    ]
}