{
    "product_id": "1095576",
    "url": "https://shopino.app/product/1095576",
    "main_category": "مردانه",
    "sub_category": "رکابی مردانه",
    "title": "کاور فوتبال ورزشی 1991 مدل CA1903 Pi",
    "description": "ارتفاععرض کارسایز7153فری سایزابعاد تا 1 سانتی متر تلرانس دارندابعاد به سانتی متر می باشداگر بین 2 سایز هستید برای جذب پوشیدن سایز کوچیک تر و برای آزاد پوشیدن سایز برزگتر را انتخاب نمایید",
    "price": "199,000",
    "old_price": "340,000",
    "discount_percentage": "41 %",
    "shop_url": "https://shopino.app/shops/1454",
    "shop_name": "نوزده نود و یک",
    "images": [
        "assets/مردانه/رکابی مردانه/1095576/8a825823302d00173110efd74b6bc5ca.jpg",
        "assets/مردانه/رکابی مردانه/1095576/0167c082719619a5bd775a8a65adb2ab.jpg",
        "assets/مردانه/رکابی مردانه/1095576/1a155382dd9750c3c2f4be273b1a6753.jpg",
        "assets/مردانه/رکابی مردانه/1095576/fa74fda3397ea15483e19c52ccf06957.jpg",
        "assets/مردانه/رکابی مردانه/1095576/8a825823302d00173110efd74b6bc5ca.jpg",
        "assets/مردانه/رکابی مردانه/1095576/0167c082719619a5bd775a8a65adb2ab.jpg",
        "assets/مردانه/رکابی مردانه/1095576/1a155382dd9750c3c2f4be273b1a6753.jpg",
        "assets/مردانه/رکابی مردانه/1095576/fa74fda3397ea15483e19c52ccf06957.jpg",
        "assets/مردانه/رکابی مردانه/1095576/d305c4a67345cc0512f28fbe0ae65a10.jpg",
        "assets/مردانه/رکابی مردانه/1095576/d305c4a67345cc0512f28fbe0ae65a10.jpg",
        "assets/مردانه/رکابی مردانه/1095576/d305c4a67345cc0512f28fbe0ae65a10.jpg"
    ],
    "related_lists": [
        {
            "name": "رکابی مردانه نسکافه‌ای"
        },
        {
            "name": "ست رکابی و شلوارک کپ مردانه"
        },
        {
            "name": "رکابی نایک تنفسی مردانه"
        }
    ]
}