{
    "product_id": "720727",
    "url": "https://shopino.app/product/720727",
    "main_category": "مردانه",
    "sub_category": "جوراب مردانه",
    "title": "جوراب مردانه",
    "description": "جوراب مردانه ساقدار\n\tبافته شده از الیاف با کیفیت\n\tدارای کشبافت بخش انتهای جوراب\n\tاستفاده از الیاف پلی امید جهت ایجاد حالت ارتجاعی و کشسانی بیشتر\n\tشناسه محصول: 2411320",
    "price": "No Price",
    "old_price": null,
    "discount_percentage": null,
    "shop_url": "https://shopino.app/shops/156",
    "shop_name": "پوشاک کروم",
    "images": [
        "assets/مردانه/جوراب مردانه/720727/35bb26d381547838f77afdb0c34d87f3.jpg",
        "assets/مردانه/جوراب مردانه/720727/82b53bd705ac1a74bbf4fe9745c80705.jpg",
        "assets/مردانه/جوراب مردانه/720727/6e18b780dff32ab8906bfe79e4597130.jpg",
        "assets/مردانه/جوراب مردانه/720727/35bb26d381547838f77afdb0c34d87f3.jpg",
        "assets/مردانه/جوراب مردانه/720727/82b53bd705ac1a74bbf4fe9745c80705.jpg",
        "assets/مردانه/جوراب مردانه/720727/6e18b780dff32ab8906bfe79e4597130.jpg",
        "assets/مردانه/جوراب مردانه/720727/41636033_1941023815985306_6097891418926219264_n.jpg",
        "assets/مردانه/جوراب مردانه/720727/41636033_1941023815985306_6097891418926219264_n.jpg",
        "assets/مردانه/جوراب مردانه/720727/41636033_1941023815985306_6097891418926219264_n.jpg"
    ],
    "related_lists": [
        {
            "name": "جوراب مردانه زمستانه"
        },
        {
            "name": "پک جوراب ساق‌دار مردانه"
        },
        {
            "name": "جوراب مردانه صورتی"
        }
    ]
}