{
    "product_id": "1183902",
    "url": "https://shopino.app/product/1183902",
    "main_category": "ุฒูุงูู",
    "sub_category": "ุณุงุฑุงููู ุฒูุงูู",
    "title": "ุณุงุฑุงูู ู ฺฉูุฑุจูุฏ ูุฏู ูพุฑ ุฏุฎุช",
    "description": "ุชูุถุญุงุช\n                                            ูุฎูู ุจุงฺฉูุช ุฎุฑุฌฺฉุงุฑ ุณูุฒู ุฏูุฒ ูุงุฑุฏุงุช. ๐นุฏูุฑ ุณูู ุญุฏูุฏ ฑฐฐ ุณุงูุช ๐นุฏูุฑ ุจุงุฒู ุญุฏูุฏ ดฒ ุณุงูุช ๐นูุฏ ุขุณุชู ุญุฏูุฏ ตต ุณุงูุช ๐นูุฏ ุณุงุฑุงููู ุญุฏูุฏ ฑณฐ ุณุงูุช ๐นุฏูุฑ ุณูู ุณุงุฑุงูู ุญุฏูุฏ ฑฑด ุณุงูุช",
    "price": "No Price",
    "old_price": null,
    "discount_percentage": null,
    "shop_url": "https://shopino.app/shops/1587",
    "shop_name": "ุจูุชฺฉ ุฏููู",
    "images": [
        "assets/ุฒูุงูู/ุณุงุฑุงููู ุฒูุงูู/1183902/4bdd61737cef2948c1b3d7a5e513e50b.jpg",
        "assets/ุฒูุงูู/ุณุงุฑุงููู ุฒูุงูู/1183902/759dc3cd331e292ac1fac1121f6d325e.jpg",
        "assets/ุฒูุงูู/ุณุงุฑุงููู ุฒูุงูู/1183902/5d59023055ecf53693ad74cce86b9840.jpg",
        "assets/ุฒูุงูู/ุณุงุฑุงููู ุฒูุงูู/1183902/63a007d1b8e1a269891ae29055533934.jpg",
        "assets/ุฒูุงูู/ุณุงุฑุงููู ุฒูุงูู/1183902/bf8d4785d7c7e4285943c7a4b49c81c7.jpg",
        "assets/ุฒูุงูู/ุณุงุฑุงููู ุฒูุงูู/1183902/925b9ed22a417b31980f5df7a4a7cf4f.jpg",
        "assets/ุฒูุงูู/ุณุงุฑุงููู ุฒูุงูู/1183902/f04d58475f9f202c059818acf9cd6774.jpg",
        "assets/ุฒูุงูู/ุณุงุฑุงููู ุฒูุงูู/1183902/4bdd61737cef2948c1b3d7a5e513e50b.jpg",
        "assets/ุฒูุงูู/ุณุงุฑุงููู ุฒูุงูู/1183902/759dc3cd331e292ac1fac1121f6d325e.jpg",
        "assets/ุฒูุงูู/ุณุงุฑุงููู ุฒูุงูู/1183902/5d59023055ecf53693ad74cce86b9840.jpg",
        "assets/ุฒูุงูู/ุณุงุฑุงููู ุฒูุงูู/1183902/63a007d1b8e1a269891ae29055533934.jpg",
        "assets/ุฒูุงูู/ุณุงุฑุงููู ุฒูุงูู/1183902/bf8d4785d7c7e4285943c7a4b49c81c7.jpg",
        "assets/ุฒูุงูู/ุณุงุฑุงููู ุฒูุงูู/1183902/925b9ed22a417b31980f5df7a4a7cf4f.jpg",
        "assets/ุฒูุงูู/ุณุงุฑุงููู ุฒูุงูู/1183902/f04d58475f9f202c059818acf9cd6774.jpg",
        "assets/ุฒูุงูู/ุณุงุฑุงููู ุฒูุงูู/1183902/a4962ce8ed664981789247cefc3142a1.jpg",
        "assets/ุฒูุงูู/ุณุงุฑุงููู ุฒูุงูู/1183902/a4962ce8ed664981789247cefc3142a1.jpg",
        "assets/ุฒูุงูู/ุณุงุฑุงููู ุฒูุงูู/1183902/a4962ce8ed664981789247cefc3142a1.jpg"
    ],
    "related_lists": [
        {
            "name": "ุณุงุฑุงููู ุฒูุงูู ูุดฺฉ"
        },
        {
            "name": "ุณุงุฑุงููู ูุจุฑู ุฒูุงูู"
        },
        {
            "name": "ุณุงุฑุงููู ุฒูุงูู ุณุงุฒ L"
        }
    ]
}