{
    "product_id": "1112653",
    "url": "https://shopino.app/product/1112653",
    "main_category": "زنانه",
    "sub_category": "دستکش زنانه",
    "title": "دستکش یک انگشتی آجدار کوتاه 09152702",
    "description": "دستکش یک انگشتی آجدار کوتاه\n% ویسکوز - % پلی استر - % پلی آمید\nهیچ چیزی قابل استفاده نیست - خشک شویی نمی توان انجام داد - شستشوی ظریف با ماشین در دمای درجه سانتیگراد - اتوکشی وجود ندارد - غلتکی را نمی توان انجام داد\nالگو: آجدار\nجنسیت: زن\nبرند: Bershka\nرنگ: مشکی\nنوع پارچه: بافندگی",
    "price": "No Price",
    "old_price": null,
    "discount_percentage": null,
    "shop_url": "https://shopino.app/shops/1671",
    "shop_name": "ترندی‌تو",
    "images": [
        "assets/زنانه/دستکش زنانه/1112653/482c26b530a3937e8e172df4fdaceb32.jpg",
        "assets/زنانه/دستکش زنانه/1112653/3d38c1ae8807487fc97deb4ad1afac7a.jpg",
        "assets/زنانه/دستکش زنانه/1112653/1fece959c580773286cb591e9212b6c3.jpg",
        "assets/زنانه/دستکش زنانه/1112653/482c26b530a3937e8e172df4fdaceb32.jpg",
        "assets/زنانه/دستکش زنانه/1112653/3d38c1ae8807487fc97deb4ad1afac7a.jpg",
        "assets/زنانه/دستکش زنانه/1112653/1fece959c580773286cb591e9212b6c3.jpg",
        "assets/زنانه/دستکش زنانه/1112653/5bda2d22adb712edf035b4e3df734392.webp",
        "assets/زنانه/دستکش زنانه/1112653/5bda2d22adb712edf035b4e3df734392.webp",
        "assets/زنانه/دستکش زنانه/1112653/5bda2d22adb712edf035b4e3df734392.webp"
    ],
    "related_lists": [
        {
            "name": "دستکش زاپ دار زنانه"
        },
        {
            "name": "دستکش چرم نیمه زنانه"
        },
        {
            "name": "دستکش شمسه زنانه"
        }
    ]
}