{
    "product_id": "1370623",
    "url": "https://shopino.app/product/1370623",
    "main_category": "زنانه",
    "sub_category": "شال زنانه",
    "title": "شال لمه مشکی",
    "description": "شال لمه مشکی\nمدل چهارخانه اکلیلی\nابعاد: طول 162،عرض 80\nاین شال سر نیست و به راحتی می توانید با هر رنگی ست کنید.",
    "price": "No Price",
    "old_price": null,
    "discount_percentage": null,
    "shop_url": "https://shopino.app/shops/1730",
    "shop_name": "چالکو",
    "images": [
        "assets/زنانه/شال زنانه/1370623/2f04929b6ec2dd548b47df7e961af4d6.jpg",
        "assets/زنانه/شال زنانه/1370623/cd00a80ce417d38171cf44cbbf32b55b.jpg",
        "assets/زنانه/شال زنانه/1370623/2f04929b6ec2dd548b47df7e961af4d6.jpg",
        "assets/زنانه/شال زنانه/1370623/cd00a80ce417d38171cf44cbbf32b55b.jpg",
        "assets/زنانه/شال زنانه/1370623/8f0de2ec2ae1fa4f5e3d6906e1a8807c.jpg",
        "assets/زنانه/شال زنانه/1370623/8f0de2ec2ae1fa4f5e3d6906e1a8807c.jpg",
        "assets/زنانه/شال زنانه/1370623/8f0de2ec2ae1fa4f5e3d6906e1a8807c.jpg"
    ],
    "related_lists": [
        {
            "name": "شال طرح هاوایی زنانه"
        },
        {
            "name": "شال پلیسه مورب زنانه"
        },
        {
            "name": "شال تک الیاف زنانه"
        }
    ]
}