{
    "product_id": "987148",
    "url": "https://shopino.app/product/987148",
    "main_category": "زنانه",
    "sub_category": "شومیز زنانه",
    "title": "شومیز سفید ترک با رگه دوزی آبی برند ESQ طرح آلما",
    "description": "جدول سایزبندی دقیق شومیز سفید ترک با رگه دوزی آبی برند ESQ طرح آلما\n\n\n\n   سایزبندی\n   دورسینه\n    دور بازو\n    قد جلو\n قد پشت\n\n\n          S\n       96\n       28\n       60\n      65\n\n\n         M\n      102\n       30\n       60\n      65\n\n\n         L\n      104\n       32\n       60\n      65",
    "price": "No Price",
    "old_price": null,
    "discount_percentage": null,
    "shop_url": "https://shopino.app/shops/1661",
    "shop_name": "چینود",
    "images": [
        "assets/زنانه/شومیز زنانه/987148/697ca55b2ff4dca6a1d5d1aabad976ab.jpg",
        "assets/زنانه/شومیز زنانه/987148/ec6bcb1920d55e874d24b25cd0c1356b.jpg",
        "assets/زنانه/شومیز زنانه/987148/cd9d08b31d4e063e7b645ec723855c5f.jpg",
        "assets/زنانه/شومیز زنانه/987148/1a0850d2615e9f42d1a3fd64481f7d57.jpg",
        "assets/زنانه/شومیز زنانه/987148/697ca55b2ff4dca6a1d5d1aabad976ab.jpg",
        "assets/زنانه/شومیز زنانه/987148/ec6bcb1920d55e874d24b25cd0c1356b.jpg",
        "assets/زنانه/شومیز زنانه/987148/cd9d08b31d4e063e7b645ec723855c5f.jpg",
        "assets/زنانه/شومیز زنانه/987148/1a0850d2615e9f42d1a3fd64481f7d57.jpg",
        "assets/زنانه/شومیز زنانه/987148/84874af5d629b0b54d7c73b8e0fe7cb3.jpg",
        "assets/زنانه/شومیز زنانه/987148/84874af5d629b0b54d7c73b8e0fe7cb3.jpg",
        "assets/زنانه/شومیز زنانه/987148/84874af5d629b0b54d7c73b8e0fe7cb3.jpg"
    ],
    "related_lists": [
        {
            "name": "شومیز کتان نیلا زنانه"
        },
        {
            "name": "شومیز طرح دار ساتن زنانه"
        },
        {
            "name": "شومیز marshmelow زنانه"
        }
    ]
}