{
    "product_id": "977552",
    "url": "https://shopino.app/product/977552",
    "main_category": "مردانه",
    "sub_category": "گردنبند مردانه",
    "title": "زنجیر گردنبند کارتیر مردانه طلایی",
    "description": "زنجیر کارتیر مردانه طلایی بلند\nکیفیت عالی\nگردنبند استیل مردانه طلایی\nطول ۵۵ سانتیمتر\nرنگ ثابت\nآبکاری طلا\nضدحساسیت\nبرای ماندگاری بیشتر مواد شوینده نزنید",
    "price": "No Price",
    "old_price": null,
    "discount_percentage": null,
    "shop_url": "https://shopino.app/shops/1653",
    "shop_name": "زرین شاپ",
    "images": [
        "assets/مردانه/گردنبند مردانه/977552/9374c06a765ead32f32f43761a5669c7.jpg",
        "assets/مردانه/گردنبند مردانه/977552/9374c06a765ead32f32f43761a5669c7.jpg",
        "assets/مردانه/گردنبند مردانه/977552/7b90180c9712594e67901f60c68733dc.jpg",
        "assets/مردانه/گردنبند مردانه/977552/7b90180c9712594e67901f60c68733dc.jpg",
        "assets/مردانه/گردنبند مردانه/977552/7b90180c9712594e67901f60c68733dc.jpg"
    ],
    "related_lists": [
        {
            "name": "گردن‌بند سیگار بهمن مردانه"
        },
        {
            "name": "گردن‌بند استیل cartier مردانه"
        },
        {
            "name": "گردن‌بند طلایی مدل allah مردانه"
        }
    ]
}