{
    "product_id": "875623",
    "url": "https://shopino.app/product/875623",
    "main_category": "زنانه",
    "sub_category": "عطر زنانه",
    "title": "ادو پرفیوم زنانه پشن بورلی هیلز پولو",
    "description": "خانواده بویایی: شیپر، گلی\nنت های بالایی: انگور فرنگی سیاه، سرخالو و میوه های قرمز\nنت های میانی: گل رز، گل صدتومانی و نت های دریایی\nنت های پایه: چوب صندل، مشک و نعناع هندی\nنت بالایی این عطر نخست با رایحه های میوه ای انگور فرنگی سیاه، سرخالو و میوه های قرمز رنگ آغاز می شود. \nاما با گذشت زمانی کوتاه شمیم معطر گل های رز و گل صدتومانی به مشام می رسد که با نت های باطراوت دریایی همراه می شود. \nدر نهایت نیز رایحه های ماندگار چوب صندل، مشک و گیاه نعناع هندی از نت پایه این عطر بر جای می ماند. ادو پرفیوم Passion محصولی از شرکت بورلی هیلز پولو کلاب است و برای استفاده خانم ها مناسب است.",
    "price": "3,059,910",
    "old_price": "3,399,900",
    "discount_percentage": "10 %",
    "shop_url": "https://shopino.app/shops/1538",
    "shop_name": "لیلیان مد",
    "images": [
        "assets/زنانه/عطر زنانه/875623/43ec0c8c2151e3d83f0225bffbfa1fe2.jpg",
        "assets/زنانه/عطر زنانه/875623/43ec0c8c2151e3d83f0225bffbfa1fe2.jpg",
        "assets/زنانه/عطر زنانه/875623/281605713_186464973712363_1278998934672970399_n.jpg",
        "assets/زنانه/عطر زنانه/875623/281605713_186464973712363_1278998934672970399_n.jpg",
        "assets/زنانه/عطر زنانه/875623/281605713_186464973712363_1278998934672970399_n.jpg"
    ],
    "related_lists": []
}