{
    "product_id": "297062",
    "url": "https://shopino.app/product/297062",
    "main_category": "زنانه",
    "sub_category": "شال گردن زنانه",
    "title": "شالگردن کلاسیک پشمی",
    "description": "❌ آخرین موجودی این محصول فروخته شده اما در صورت ثبت سفارش امکان بافت مجدد خواهد داشت.تاریخ ارسال ۲۰ تا ۳۰ روز کاری بسته به حجم سفارشها خواهد بود.شالگردن کلاسیک تمام کشبافابعاد : عرض ۱۸ در طول ۲۱۰ سانتیبا تزیین ۶ عدد پوم پوم کامواییدستبافخیلی گرم ۴۹٪ پشم",
    "price": "No Price",
    "old_price": null,
    "discount_percentage": null,
    "shop_url": "https://shopino.app/shops/1471",
    "shop_name": "پنج",
    "images": [
        "assets/زنانه/شال گردن زنانه/297062/8e238f36856106bc2a79244d0e0152d6.jpg",
        "assets/زنانه/شال گردن زنانه/297062/f72cb3ebc8f04ccce715b8af94bb3a4b.jpg",
        "assets/زنانه/شال گردن زنانه/297062/5afb3c29d85075c2140893f71198579f.jpg",
        "assets/زنانه/شال گردن زنانه/297062/8e238f36856106bc2a79244d0e0152d6.jpg",
        "assets/زنانه/شال گردن زنانه/297062/f72cb3ebc8f04ccce715b8af94bb3a4b.jpg",
        "assets/زنانه/شال گردن زنانه/297062/5afb3c29d85075c2140893f71198579f.jpg",
        "assets/زنانه/شال گردن زنانه/297062/cf16b1f1ffdb0136095a30953c5ec82b.webp",
        "assets/زنانه/شال گردن زنانه/297062/cf16b1f1ffdb0136095a30953c5ec82b.webp",
        "assets/زنانه/شال گردن زنانه/297062/cf16b1f1ffdb0136095a30953c5ec82b.webp"
    ],
    "related_lists": [
        {
            "name": "شال گردن بافت درشت طرح دار زنانه"
        },
        {
            "name": "شال گردن رینگی و کلاه زنانه"
        },
        {
            "name": "شال پشمی نازک چهارخونه زنانه"
        }
    ]
}