{
    "product_id": "1173038",
    "url": "https://shopino.app/product/1173038",
    "main_category": "ุฒูุงูู",
    "sub_category": "ุดุงู ฺฏุฑุฏู ุฒูุงูู",
    "title": "ุดุงู ฺฉูุงู ุฌูุฑุฌุง",
    "description": "ุดุงู ฺฉูุงู ุฌูุฑุฌุง\nุฌูุณ : ุจุงูุช ุจุณุงุฑ ูุทู ูุฎ ุชุฑฺฉ\nโฃุฑูฺฏ ุจูุฏ : ุทูุณ, ูุดฺฉ\nโฃุณุงุฒ ูุง : ุขุฒุงุฏ\nโูุฏฺฉูุงู 35\nโ ุฏู ูุงู\nโูุฏ ุดุงู 110\nโุดุงู ฺฏุฑุฏู ุฑูฺฏ ูู ุจุงุดุฏ\nฺฉูุช ุนุงุงุงุงุงู๐นโค๏ธ",
    "price": "No Price",
    "old_price": null,
    "discount_percentage": null,
    "shop_url": "https://shopino.app/shops/1707",
    "shop_name": "ุฏุฌ  ูุงฺฉุช",
    "images": [
        "assets/ุฒูุงูู/ุดุงู ฺฏุฑุฏู ุฒูุงูู/1173038/b9c9e0ae6e7b23dde20611ccfbd22832.jpg",
        "assets/ุฒูุงูู/ุดุงู ฺฏุฑุฏู ุฒูุงูู/1173038/84c6e063c2f1072360704c8b1b97bb3a.jpg",
        "assets/ุฒูุงูู/ุดุงู ฺฏุฑุฏู ุฒูุงูู/1173038/b9c9e0ae6e7b23dde20611ccfbd22832.jpg",
        "assets/ุฒูุงูู/ุดุงู ฺฏุฑุฏู ุฒูุงูู/1173038/84c6e063c2f1072360704c8b1b97bb3a.jpg",
        "assets/ุฒูุงูู/ุดุงู ฺฏุฑุฏู ุฒูุงูู/1173038/3dfec48422a17289b1ca177ab4d65ce9.webp",
        "assets/ุฒูุงูู/ุดุงู ฺฏุฑุฏู ุฒูุงูู/1173038/3dfec48422a17289b1ca177ab4d65ce9.webp",
        "assets/ุฒูุงูู/ุดุงู ฺฏุฑุฏู ุฒูุงูู/1173038/3dfec48422a17289b1ca177ab4d65ce9.webp"
    ],
    "related_lists": [
        {
            "name": "ุดุงู ู ฺฉูุงู ูุฑุงูุณู ุฒูุงูู"
        },
        {
            "name": "ฺฉูุงู ฺฏูุดโุฏุงุฑ ู ุดุงู ุฒูุงูู"
        },
        {
            "name": "ุดุงู ู ฺฉูุงู ุฏู ูพูู ุฒูุงูู"
        }
    ]
}