{
    "product_id": "1373284",
    "url": "https://shopino.app/product/1373284",
    "main_category": "مردانه",
    "sub_category": "هودی مردانه",
    "title": "هودی مردانه زرد با سویشرت گلدوزی 6145",
    "description": "نوع بازو: بازوی استاندارد\nنوع جیبی: با جیب\nنوع بسته شدن: توری\nنوع یقه: یقه دوچرخه\nمنطقه استفاده: روزانه\nنوع پارچه: بافندگی\nرنگ: سبز\nبرش: طبیعی\nارتفاع / اندازه: بلند\nجیبی: فقط\nالگو: سر راست\nبرند: Madmext",
    "price": "No Price",
    "old_price": null,
    "discount_percentage": null,
    "shop_url": "https://shopino.app/shops/1671",
    "shop_name": "ترندی‌تو",
    "images": [
        "assets/مردانه/هودی مردانه/1373284/18684e45fde79c77d2b927d0b2082e6c.jpg",
        "assets/مردانه/هودی مردانه/1373284/cd0162eab70de539e963221f662e260d.jpg",
        "assets/مردانه/هودی مردانه/1373284/f4c065f630ff8b549473a24c2edc9d9d.jpg",
        "assets/مردانه/هودی مردانه/1373284/18684e45fde79c77d2b927d0b2082e6c.jpg",
        "assets/مردانه/هودی مردانه/1373284/cd0162eab70de539e963221f662e260d.jpg",
        "assets/مردانه/هودی مردانه/1373284/f4c065f630ff8b549473a24c2edc9d9d.jpg",
        "assets/مردانه/هودی مردانه/1373284/5bda2d22adb712edf035b4e3df734392.webp",
        "assets/مردانه/هودی مردانه/1373284/5bda2d22adb712edf035b4e3df734392.webp",
        "assets/مردانه/هودی مردانه/1373284/5bda2d22adb712edf035b4e3df734392.webp"
    ],
    "related_lists": [
        {
            "name": "هودی رینگر دورس سه‌نخ خارخورده مردانه"
        },
        {
            "name": "هودی مردانه رنگ مشکی ساده مردانه"
        },
        {
            "name": "هودی مردانه دورس مردانه"
        }
    ]
}