{
    "product_id": "1195153",
    "url": "https://shopino.app/product/1195153",
    "main_category": "مردانه",
    "sub_category": "لباس خواب و راحتی مردانه",
    "title": "ست بلوز شلوار مردانه مدل kenet (زغالی )",
    "description": "ست بلوز شلوار kenet (زغالی )کد 6130\n\nجنس بلوز : ملانژ\nجنس شلوار : ملانژ\nسایز بندی : XL/XXL\n\nسایز XL\nقد بلوز : 70CM\nقد شلوار : 105CM\nقد فاق : 35CM\nقد آستین : 57CM\nعرض شانه : 43CM\nعرض سینه : 50CM\nسایز :XXL\n\nقد بلوز : 73CM\nقد شلوار : 105CM\nقد فاق : 35CM\nقد آستین : 62CM\nعرض شانه : 49CM\nعرض سینه : 53CM\nقیمت استثنایی فقط 348,000",
    "price": "No Price",
    "old_price": null,
    "discount_percentage": null,
    "shop_url": "https://shopino.app/shops/1579",
    "shop_name": "Shikstore",
    "images": [
        "assets/مردانه/لباس خواب و راحتی مردانه/1195153/721d5991d0c1036f4fad7f53f6d6cbe6.jpg",
        "assets/مردانه/لباس خواب و راحتی مردانه/1195153/1f2493d114cbc71bc486eb03ad23a848.jpg",
        "assets/مردانه/لباس خواب و راحتی مردانه/1195153/721d5991d0c1036f4fad7f53f6d6cbe6.jpg",
        "assets/مردانه/لباس خواب و راحتی مردانه/1195153/1f2493d114cbc71bc486eb03ad23a848.jpg",
        "assets/مردانه/لباس خواب و راحتی مردانه/1195153/183706593_480025083318078_5959003596200767324_n.jpg",
        "assets/مردانه/لباس خواب و راحتی مردانه/1195153/183706593_480025083318078_5959003596200767324_n.jpg",
        "assets/مردانه/لباس خواب و راحتی مردانه/1195153/183706593_480025083318078_5959003596200767324_n.jpg"
    ],
    "related_lists": [
        {
            "name": "سویشرت و شلوار پورش مردانه"
        },
        {
            "name": "پیراهن و شلوارک مراکش مردانه"
        },
        {
            "name": "ست تی‌شرت و شلوار مردانه"
        }
    ]
}