{
    "product_id": "1208160",
    "url": "https://shopino.app/product/1208160",
    "main_category": "زنانه",
    "sub_category": "سارافون زنانه",
    "title": "ست یلدایی سارافون و جلیقه کد 1189",
    "description": "سه تکه  شیک یلدایی\nمیتونی برای عید نوروز هم بپوشی\nژیله  و پیراهن و کمربند و بسیار شیک و خاص \n به هم متصل نیست\nجنس رویه ژاکارد+  مازراتی  درجه یک و گرم بالا\nبا این ست یه استایل عالی بساز\n مناسب ۳۸ تا ۵۰\nسایز ۱ مناسب۳۸ تا ۴۴\nسایز ۲ مناسب۴۶ تا ۵۰\nقد  ژیله تقریبا  ۶۰\nقد زیره (سارافون) تقریبا ۱۳۰\nدرخرید آنلاین تفاوت یک الی دو درجه تغییر رنگ به علت تفاوت تغییر نور صفحه نمایشگر گوشی در نظر گرفته شود.\nارسال بعد از 15 روز کاری است.",
    "price": "No Price",
    "old_price": null,
    "discount_percentage": null,
    "shop_url": "https://shopino.app/shops/1571",
    "shop_name": "مزون آماندا",
    "images": [
        "assets/زنانه/سارافون زنانه/1208160/52f0ac82caac9e4cdd7dd77aa6076745.jpg",
        "assets/زنانه/سارافون زنانه/1208160/dd022d235cef8eccc444492f45e047a1.jpg",
        "assets/زنانه/سارافون زنانه/1208160/52f0ac82caac9e4cdd7dd77aa6076745.jpg",
        "assets/زنانه/سارافون زنانه/1208160/dd022d235cef8eccc444492f45e047a1.jpg",
        "assets/زنانه/سارافون زنانه/1208160/50f9c58694db6de934eaa7c5fcbf4a87.webp",
        "assets/زنانه/سارافون زنانه/1208160/50f9c58694db6de934eaa7c5fcbf4a87.webp",
        "assets/زنانه/سارافون زنانه/1208160/50f9c58694db6de934eaa7c5fcbf4a87.webp"
    ],
    "related_lists": [
        {
            "name": "سارافون زنانه سایز 34"
        },
        {
            "name": "سارافون زنانه آستین بلند کراش زنانه"
        },
        {
            "name": "سارافون زنانه سر شانه چین زنانه"
        }
    ]
}