{
    "product_id": "1041773",
    "url": "https://shopino.app/product/1041773",
    "main_category": "مردانه",
    "sub_category": "کتونی مردانه",
    "title": "کتانی مدکس گازولین مشکی",
    "description": "کتانی مدکس گازولین مشکی - GAAZOLIN\nرویه چرم طبیعی گوساله با پرداخت فلوتر\nآستر چرم طبیعی\nکفی طبی چرم طبیعی\nزیره رابر تخت\nمناسب برای استایل روزانه\nچهار فصل\nمردانه\nساختار\nمدکس - Madox رویه تهیه شده از چرم طبیعی گاوی دست رنگ؛ آستر و کفی داخلی تمام چرم طبیعی تنفسی چهار فصل، کفی طبی به کار رفته در مدکس باعث می شود که برای استفاده در ساعات طولانی شبانه روز کاربردی شود، زیره از جنس رابر می‌باشد.\nدرباره مدل\nمدکس - Madox از سری کتانی های زیره تخت برند گازولین با استایل روزمره و برش های جذاب؛در این مدل از ظرافت خاصی در دوخت استفاده شده، گویی که یک اثر نقاشی از کفش را پایتان کرده‌اید؛ با اینکه مدکس یک کتانی روزمره است اما به دلیل همین عمق هنری بهتر است با استایل های ویژه‌ای که برایتان مهم است ست شود.\nاینستاگرام رزمد",
    "price": "No Price",
    "old_price": null,
    "discount_percentage": null,
    "shop_url": "https://shopino.app/shops/683",
    "shop_name": "رزمد",
    "images": [
        "assets/مردانه/کتونی مردانه/1041773/f85dd07826782d057b5d3b1e5b594e93.jpg",
        "assets/مردانه/کتونی مردانه/1041773/e3b67f9fb5eb4bd152540d46cfb9e4fd.jpg",
        "assets/مردانه/کتونی مردانه/1041773/226ff91c88f94c49ddf42e7379476f03.jpg",
        "assets/مردانه/کتونی مردانه/1041773/54e05c5303ae1f1c341f39b2405895bf.jpg",
        "assets/مردانه/کتونی مردانه/1041773/3244126ad2b386b2d89d65c1332a6e42.jpg",
        "assets/مردانه/کتونی مردانه/1041773/ca9c77988b8cf094db461e57d1249b26.jpg",
        "assets/مردانه/کتونی مردانه/1041773/f85dd07826782d057b5d3b1e5b594e93.jpg",
        "assets/مردانه/کتونی مردانه/1041773/e3b67f9fb5eb4bd152540d46cfb9e4fd.jpg",
        "assets/مردانه/کتونی مردانه/1041773/226ff91c88f94c49ddf42e7379476f03.jpg",
        "assets/مردانه/کتونی مردانه/1041773/54e05c5303ae1f1c341f39b2405895bf.jpg",
        "assets/مردانه/کتونی مردانه/1041773/3244126ad2b386b2d89d65c1332a6e42.jpg",
        "assets/مردانه/کتونی مردانه/1041773/ca9c77988b8cf094db461e57d1249b26.jpg",
        "assets/مردانه/کتونی مردانه/1041773/336842366_3452663725011131_5579293991905378154_n.jpg",
        "assets/مردانه/کتونی مردانه/1041773/336842366_3452663725011131_5579293991905378154_n.jpg",
        "assets/مردانه/کتونی مردانه/1041773/336842366_3452663725011131_5579293991905378154_n.jpg"
    ],
    "related_lists": [
        {
            "name": "کفش اسپرت مردانه Clarks مردانه"
        },
        {
            "name": "ونس آدیداس کاستوم مردانه"
        },
        {
            "name": "کتانی مردانه خردلی"
        }
    ]
}