{
    "product_id": "1374444",
    "url": "https://shopino.app/product/1374444",
    "main_category": "زنانه",
    "sub_category": "ست لباس زنانه",
    "title": "ست کت و سارافون یلدایی گندم کد : K0002",
    "description": "شب یلدا ، که به عنوان شب چله نیز شناخته می‌شود، یکی از قدیمی‌ترین جشن‌های ایرانی است که در آخرین شب پاییز، یعنی شب ۳۰ آذر، برگزار می‌شود.\nست گندم جذاب ترین ست سارافون و کت برای این جشن و دورهمی با عشق و شکوه یلدا برای شما طراحی و دوخت شده است .\nاین سارافون زیبا ار جنس کرپ اندونزی دوخت شده است که قسمت دامن کار کلوش بوده و مدل یقه کار نیز یقه گرد بوده و لازم به ذکر است سارافون حلقه ای و بدون آستین است که کت مخمل سوزن دوزی مدل آن را تکمیل میکند.\nاین کت دلبر یلدایی با طراحی گل های ریز و درشت و گلبرگ های متفاوت قرمز مخمل دوزی بر روی پارچه مخمل مشکی منحصر به فرد بوده و به شکوه و زیبایی کار افزوده .\nمدل سرشانه کار ساده بوده و همچنین مدل سر آستین این کت با تکه نواری پارچه کرپ اندونزی ست با سارافون به صورت پاکتی و ساده دوخت و طراحی شده که قد آستین آن نسبت به بقیه مدل ها بلندتر بوده و حدودی 55 سانتی متر است .\nدر قسمت کمر سارافون یک نوار پهن مشابه با پارچه کت دوخت و طراحی شده.\nقدکار سارافون 120 سانتی متر و فری سایز مناسب سایز 36 تا 46 است .",
    "price": "No Price",
    "old_price": null,
    "discount_percentage": null,
    "shop_url": "https://shopino.app/shops/1677",
    "shop_name": "مروارید شب",
    "images": [
        "assets/زنانه/ست لباس زنانه/1374444/f7d1524911ca76ac156f43863b147963.jpg",
        "assets/زنانه/ست لباس زنانه/1374444/f353f52761adbc35097b9cc68fe4607b.jpg",
        "assets/زنانه/ست لباس زنانه/1374444/eb55299b7525d84e6fab93f64f082292.jpg",
        "assets/زنانه/ست لباس زنانه/1374444/87d2bf7f3f516288cdd5818e404baba2.jpg",
        "assets/زنانه/ست لباس زنانه/1374444/6854de7ee0faaa24d44dad947d1ab6b8.jpg",
        "assets/زنانه/ست لباس زنانه/1374444/d0da67551b5b316e21f2eb7b42dedef5.jpg",
        "assets/زنانه/ست لباس زنانه/1374444/3e8bc9d88605d71b7a7b47974e8581bf.jpg",
        "assets/زنانه/ست لباس زنانه/1374444/f7d1524911ca76ac156f43863b147963.jpg",
        "assets/زنانه/ست لباس زنانه/1374444/f353f52761adbc35097b9cc68fe4607b.jpg",
        "assets/زنانه/ست لباس زنانه/1374444/eb55299b7525d84e6fab93f64f082292.jpg",
        "assets/زنانه/ست لباس زنانه/1374444/87d2bf7f3f516288cdd5818e404baba2.jpg",
        "assets/زنانه/ست لباس زنانه/1374444/6854de7ee0faaa24d44dad947d1ab6b8.jpg",
        "assets/زنانه/ست لباس زنانه/1374444/d0da67551b5b316e21f2eb7b42dedef5.jpg",
        "assets/زنانه/ست لباس زنانه/1374444/3e8bc9d88605d71b7a7b47974e8581bf.jpg",
        "assets/زنانه/ست لباس زنانه/1374444/9833cc8bc1d9441f155734f07ecef41a.jpg",
        "assets/زنانه/ست لباس زنانه/1374444/9833cc8bc1d9441f155734f07ecef41a.jpg",
        "assets/زنانه/ست لباس زنانه/1374444/9833cc8bc1d9441f155734f07ecef41a.jpg"
    ],
    "related_lists": [
        {
            "name": "ست هودی و شلوار زنانه Deniz زنانه"
        },
        {
            "name": "نیم تنه و شلوار پلیسه زنانه"
        },
        {
            "name": "هودی و شلوار بیسیک زنانه"
        }
    ]
}