{
    "product_id": "1369770",
    "url": "https://shopino.app/product/1369770",
    "main_category": "زنانه",
    "sub_category": "کیف لوازم آرایش زنانه",
    "title": "جامدادی کتابی طرح فضانورد ناموجود",
    "description": null,
    "price": "No Price",
    "old_price": null,
    "discount_percentage": null,
    "shop_url": "https://shopino.app/shops/1730",
    "shop_name": "چالکو",
    "images": [
        "assets/زنانه/کیف لوازم آرایش زنانه/1369770/12b780973f24ab3cb2233c8ba1ac6cdc.jpg",
        "assets/زنانه/کیف لوازم آرایش زنانه/1369770/2a605c98c91bb051baf799256a20c2ad.jpg",
        "assets/زنانه/کیف لوازم آرایش زنانه/1369770/c13f48c511e06dcca39241ed2a545f43.jpg",
        "assets/زنانه/کیف لوازم آرایش زنانه/1369770/06f18d4309465ed81a05111e57a59f07.jpg",
        "assets/زنانه/کیف لوازم آرایش زنانه/1369770/e63f49209b92ba36c68b0eec15575c07.jpg",
        "assets/زنانه/کیف لوازم آرایش زنانه/1369770/12b780973f24ab3cb2233c8ba1ac6cdc.jpg",
        "assets/زنانه/کیف لوازم آرایش زنانه/1369770/2a605c98c91bb051baf799256a20c2ad.jpg",
        "assets/زنانه/کیف لوازم آرایش زنانه/1369770/c13f48c511e06dcca39241ed2a545f43.jpg",
        "assets/زنانه/کیف لوازم آرایش زنانه/1369770/06f18d4309465ed81a05111e57a59f07.jpg",
        "assets/زنانه/کیف لوازم آرایش زنانه/1369770/e63f49209b92ba36c68b0eec15575c07.jpg",
        "assets/زنانه/کیف لوازم آرایش زنانه/1369770/8f0de2ec2ae1fa4f5e3d6906e1a8807c.jpg",
        "assets/زنانه/کیف لوازم آرایش زنانه/1369770/8f0de2ec2ae1fa4f5e3d6906e1a8807c.jpg",
        "assets/زنانه/کیف لوازم آرایش زنانه/1369770/8f0de2ec2ae1fa4f5e3d6906e1a8807c.jpg"
    ],
    "related_lists": [
        {
            "name": "کیف آرایشیNaturehike زنانه"
        },
        {
            "name": "کیف آرایشی ویکتوریا زنانه"
        },
        {
            "name": "جامدادی سلیکونی وارداتی زنانه"
        }
    ]
}