{
    "product_id": "1047819",
    "url": "https://shopino.app/product/1047819",
    "main_category": "زنانه",
    "sub_category": "طلا و جواهر زنانه",
    "title": "انگشتر تورمالین دو رنگ",
    "description": "انگشتر تورمالین زنانهنقره ۹۲۵ابکاری رادیومجواهر کاملا طبیعیوزن جواه:۴/۳قیراطتضمین اصالت کالا✅سنگ ماهر مرداد",
    "price": "3,890,000",
    "old_price": "4,100,000",
    "discount_percentage": "5 %",
    "shop_url": "https://shopino.app/shops/1668",
    "shop_name": "سفیر کالکشن",
    "images": [
        "assets/زنانه/طلا و جواهر زنانه/1047819/538fdb21f51efac113a432aadf274870.jpg",
        "assets/زنانه/طلا و جواهر زنانه/1047819/c833ee7e392c3188c55e167b2356e109.jpg",
        "assets/زنانه/طلا و جواهر زنانه/1047819/e0928007ab1acb12adaee3f49590f900.jpg",
        "assets/زنانه/طلا و جواهر زنانه/1047819/538fdb21f51efac113a432aadf274870.jpg",
        "assets/زنانه/طلا و جواهر زنانه/1047819/c833ee7e392c3188c55e167b2356e109.jpg",
        "assets/زنانه/طلا و جواهر زنانه/1047819/e0928007ab1acb12adaee3f49590f900.jpg",
        "assets/زنانه/طلا و جواهر زنانه/1047819/269a403b487c5c35197562df563781c0.jpg",
        "assets/زنانه/طلا و جواهر زنانه/1047819/269a403b487c5c35197562df563781c0.jpg",
        "assets/زنانه/طلا و جواهر زنانه/1047819/269a403b487c5c35197562df563781c0.jpg"
    ],
    "related_lists": []
}