{
    "product_id": "1212298",
    "url": "https://shopino.app/product/1212298",
    "main_category": "مردانه",
    "sub_category": "لباس خواب و راحتی مردانه",
    "title": "ال سی وایکیکی شلوار راحتی w4jf83z8-rfh",
    "description": null,
    "price": "No Price",
    "old_price": null,
    "discount_percentage": null,
    "shop_url": "https://shopino.app/shops/1594",
    "shop_name": "تگموند",
    "images": [
        "assets/مردانه/لباس خواب و راحتی مردانه/1212298/3e7f6412f775969c6f71c5a56a1ffebf.jpg",
        "assets/مردانه/لباس خواب و راحتی مردانه/1212298/1ea2721ec5f043b5b1691a798d1dcc38.jpg",
        "assets/مردانه/لباس خواب و راحتی مردانه/1212298/3e7f6412f775969c6f71c5a56a1ffebf.jpg",
        "assets/مردانه/لباس خواب و راحتی مردانه/1212298/1ea2721ec5f043b5b1691a798d1dcc38.jpg",
        "assets/مردانه/لباس خواب و راحتی مردانه/1212298/d6e6e91ae1135f5755ee84fddddb6cfe.jpg",
        "assets/مردانه/لباس خواب و راحتی مردانه/1212298/d6e6e91ae1135f5755ee84fddddb6cfe.jpg",
        "assets/مردانه/لباس خواب و راحتی مردانه/1212298/d6e6e91ae1135f5755ee84fddddb6cfe.jpg"
    ],
    "related_lists": [
        {
            "name": "ست تی‌شرت و شلوار اسلش کبریتی مردانه"
        },
        {
            "name": "لباس خواب و راحتی مردانه زرد"
        },
        {
            "name": "ست بلوز و شلوار نیوبالانس مردانه"
        }
    ]
}