{
    "product_id": "1214368",
    "url": "https://shopino.app/product/1214368",
    "main_category": "مردانه",
    "sub_category": "کفش ورزشی مردانه",
    "title": "باشگاه - کفش ورزشی مردانه آبی سرمه ای - 03 381111",
    "description": "باشگاه پوما\nفناوری تنها: کفش لاستیکی\nنوع صحافی: توری\nنوع پایه: پایه تخت\nمواد خارجی: چرم مصنوعی\nمواد بالا: چرم اصل\nجزئیات پایداری: خیر\nبرند: Puma\nرنگ: مشکی\nجنس کفی: منسوجات\nمادهء اصلی: لاستیک\nارتفاع پاشنه: کفش پاشنه کوتاه (1 تا 4 سانتی متر)\nنوع پاشنه: کفش پاشنه تخت\nجزء مواد: Obermaterial: مصنوعی، Kuhleder; Futter: مصنوعی، Innensohle، پارچه. لاوفسوله: گومی",
    "price": "No Price",
    "old_price": null,
    "discount_percentage": null,
    "shop_url": "https://shopino.app/shops/1671",
    "shop_name": "ترندی‌تو",
    "images": [
        "assets/مردانه/کفش ورزشی مردانه/1214368/acdf17b4901f3e038f6b3d2c46e92924.jpg",
        "assets/مردانه/کفش ورزشی مردانه/1214368/70df88721dd6f0c9a5d0b4eb4f7cc11c.jpg",
        "assets/مردانه/کفش ورزشی مردانه/1214368/8de04da98326b1035d4b349aa6f5395b.jpg",
        "assets/مردانه/کفش ورزشی مردانه/1214368/4519122bdbfd08a98aacb094bc486c40.jpg",
        "assets/مردانه/کفش ورزشی مردانه/1214368/9618b91b353e58baae4ac79a7583f9ef.jpg",
        "assets/مردانه/کفش ورزشی مردانه/1214368/81a9e375da4858220847dd6789b4ab23.jpg",
        "assets/مردانه/کفش ورزشی مردانه/1214368/acdf17b4901f3e038f6b3d2c46e92924.jpg",
        "assets/مردانه/کفش ورزشی مردانه/1214368/70df88721dd6f0c9a5d0b4eb4f7cc11c.jpg",
        "assets/مردانه/کفش ورزشی مردانه/1214368/8de04da98326b1035d4b349aa6f5395b.jpg",
        "assets/مردانه/کفش ورزشی مردانه/1214368/4519122bdbfd08a98aacb094bc486c40.jpg",
        "assets/مردانه/کفش ورزشی مردانه/1214368/9618b91b353e58baae4ac79a7583f9ef.jpg",
        "assets/مردانه/کفش ورزشی مردانه/1214368/81a9e375da4858220847dd6789b4ab23.jpg",
        "assets/مردانه/کفش ورزشی مردانه/1214368/5bda2d22adb712edf035b4e3df734392.webp",
        "assets/مردانه/کفش ورزشی مردانه/1214368/5bda2d22adb712edf035b4e3df734392.webp",
        "assets/مردانه/کفش ورزشی مردانه/1214368/5bda2d22adb712edf035b4e3df734392.webp"
    ],
    "related_lists": [
        {
            "name": "کتونی ورزشی Mason مردانه"
        },
        {
            "name": "کفش ورزشی مردانه سرمه‌ای"
        },
        {
            "name": "کفش ورزشی Sply-350 مردانه"
        }
    ]
}