{
    "product_id": "1117893",
    "url": "https://shopino.app/product/1117893",
    "main_category": "زنانه",
    "sub_category": "دستکش زنانه",
    "title": "دستکش المنت دار 285 ناموجود",
    "description": "دستکش المنت دار  \n                            دارای ۳ درجه گرمایشی  \n                            ضداب  \n                            برزنتی  \n                            باتری جداگانه باید خریداری شود \n                            تنظیم کننده دور مچ \n                            قابل شستشو  \n                            شب رنگ دار",
    "price": "No Price",
    "old_price": null,
    "discount_percentage": null,
    "shop_url": "https://shopino.app/shops/1706",
    "shop_name": "ایوارا",
    "images": [
        "assets/زنانه/دستکش زنانه/1117893/f7d7b1cb356456aa7e36ae4a23e62b5a.jpg",
        "assets/زنانه/دستکش زنانه/1117893/3486900bdd51efcdbe94db99538e11ad.jpg",
        "assets/زنانه/دستکش زنانه/1117893/e97d57a64791152e3a9cd537ae731361.jpg",
        "assets/زنانه/دستکش زنانه/1117893/df242ed8f33b7f817dd7326d6dba2ac6.jpg",
        "assets/زنانه/دستکش زنانه/1117893/151565cf7b14f348c7d6cd3778a1a070.jpg",
        "assets/زنانه/دستکش زنانه/1117893/f7d7b1cb356456aa7e36ae4a23e62b5a.jpg",
        "assets/زنانه/دستکش زنانه/1117893/3486900bdd51efcdbe94db99538e11ad.jpg",
        "assets/زنانه/دستکش زنانه/1117893/e97d57a64791152e3a9cd537ae731361.jpg",
        "assets/زنانه/دستکش زنانه/1117893/df242ed8f33b7f817dd7326d6dba2ac6.jpg",
        "assets/زنانه/دستکش زنانه/1117893/151565cf7b14f348c7d6cd3778a1a070.jpg",
        "assets/زنانه/دستکش زنانه/1117893/3382b24e7e3c681a1575ee0f9c25c7cd.png",
        "assets/زنانه/دستکش زنانه/1117893/3382b24e7e3c681a1575ee0f9c25c7cd.png",
        "assets/زنانه/دستکش زنانه/1117893/3382b24e7e3c681a1575ee0f9c25c7cd.png"
    ],
    "related_lists": [
        {
            "name": "دستکش خرس گلدوزی زنانه"
        },
        {
            "name": "دستکش زنانه مشکی"
        },
        {
            "name": "دستکش اسکیمویی اندلس زنانه"
        }
    ]
}