{
    "product_id": "632110",
    "url": "https://shopino.app/product/632110",
    "main_category": "زنانه",
    "sub_category": "کیف پول زنانه",
    "title": "جاکارتی چرم مدل آراد",
    "description": "مدل آراد مدلی جذاب و زیبا که علاوه بر جاکارتی برای جای ایرپاد و جاکلیدی و فلش و ... استفاده میشه.\nدوخته شده با چرم طبیعی گاوی هورس",
    "price": "No Price",
    "old_price": null,
    "discount_percentage": null,
    "shop_url": "https://shopino.app/shops/1526",
    "shop_name": "چرم آناهید",
    "images": [
        "assets/زنانه/کیف پول زنانه/632110/3e0b588905503ed64bce0e7cbb445e63.jpg",
        "assets/زنانه/کیف پول زنانه/632110/eb85b394ea68c5614a23c56302c26e33.jpg",
        "assets/زنانه/کیف پول زنانه/632110/043ca5b9aca57d8c3bd7a5a4247c76ea.jpeg",
        "assets/زنانه/کیف پول زنانه/632110/97e3d537582b27b6ff9c99d8df3dadfe.jpeg",
        "assets/زنانه/کیف پول زنانه/632110/3e0b588905503ed64bce0e7cbb445e63.jpg",
        "assets/زنانه/کیف پول زنانه/632110/eb85b394ea68c5614a23c56302c26e33.jpg",
        "assets/زنانه/کیف پول زنانه/632110/043ca5b9aca57d8c3bd7a5a4247c76ea.jpeg",
        "assets/زنانه/کیف پول زنانه/632110/97e3d537582b27b6ff9c99d8df3dadfe.jpeg",
        "assets/زنانه/کیف پول زنانه/632110/154066072_3140449052842631_7439554346138486824_n.jpg",
        "assets/زنانه/کیف پول زنانه/632110/154066072_3140449052842631_7439554346138486824_n.jpg",
        "assets/زنانه/کیف پول زنانه/632110/154066072_3140449052842631_7439554346138486824_n.jpg"
    ],
    "related_lists": [
        {
            "name": "کیف پول جلوموبایلی زنانه"
        },
        {
            "name": "گوشواره ریش‌ریش زنانه"
        },
        {
            "name": "کیف پول دوشی کلاچ زنانه"
        }
    ]
}