{
    "product_id": "585694",
    "url": "https://shopino.app/product/585694",
    "main_category": "مردانه",
    "sub_category": "لباس ورزشی مردانه",
    "title": "ست ورزشی رکابی و شلوارک رنگ طوسی",
    "description": "ویژگی‌های ست ورزشی جذاب رنگ طوسی\n\nدر این ست از محصولات زیر استفاده شده است:\n\nشلوارک ورزشی مدل کیان\nرکابی ورزشی مدل حلقه‌ای آستین افتاده\n\nشلوارک‌های ورزشی مدل کیان، از پارچه پلی استر لاکرادار تولید شده است. وجود لاکرا در پارچه این محصول باعث شده شلوارک حالت کشسانی خوبی داشته باشد و برای حرکات تمرینی پا با دامنه‌های مختلف مناسب باشد. همچنین در کشاله این شلوارک جیب مخصوصی برای موبایل طراحی شده است.\nرکابی ورزشی مدل آستین افتاده، از پارچه پنبه لاکرا تولید شده است. این محصول به دلیل جنس پنبه‌ای که دارد تعریق را به خود جذب میکند و وجود لاکرا در پارچه این محصول باعث می‌شود محصول پس از هر بار شست و شو حالت اولیه خود را از دست ندهد.",
    "price": "733,000",
    "old_price": "772,000",
    "discount_percentage": "5 %",
    "shop_url": "https://shopino.app/shops/1542",
    "shop_name": "لباس ورزشی بادی لیام",
    "images": [
        "assets/مردانه/لباس ورزشی مردانه/585694/29efbbfc3aae0fab1df53e8b63a8c2c8.jpg",
        "assets/مردانه/لباس ورزشی مردانه/585694/c04d4a1bcddbde47362509b06754099e.jpg",
        "assets/مردانه/لباس ورزشی مردانه/585694/5e3d24c042f011292ab28ff142e6df5d.jpg",
        "assets/مردانه/لباس ورزشی مردانه/585694/29efbbfc3aae0fab1df53e8b63a8c2c8.jpg",
        "assets/مردانه/لباس ورزشی مردانه/585694/c04d4a1bcddbde47362509b06754099e.jpg",
        "assets/مردانه/لباس ورزشی مردانه/585694/5e3d24c042f011292ab28ff142e6df5d.jpg",
        "assets/مردانه/لباس ورزشی مردانه/585694/143398853_468886270940018_2315025090996391081_n.jpg",
        "assets/مردانه/لباس ورزشی مردانه/585694/143398853_468886270940018_2315025090996391081_n.jpg",
        "assets/مردانه/لباس ورزشی مردانه/585694/143398853_468886270940018_2315025090996391081_n.jpg"
    ],
    "related_lists": [
        {
            "name": "ست بهاره نایک مردانه"
        },
        {
            "name": "ست تاپ و شلوارک راک مردانه"
        },
        {
            "name": "شلوار ورزشی بغل دکمه مردانه"
        }
    ]
}