{
    "product_id": "1369284",
    "url": "https://shopino.app/product/1369284",
    "main_category": "زنانه",
    "sub_category": "ساعت زنانه",
    "title": "ساعت مجلسی نگینی زنانه HENGEN",
    "description": "قبل ارسال ساعت از لحاظ سلامت فیزیکی موتور و بدنه بطور کامل چک و تست گرفته میشوند و ساعت صد در صد سالم بدست شما دوست عزیز میرسد",
    "price": "No Price",
    "old_price": null,
    "discount_percentage": null,
    "shop_url": "https://shopino.app/shops/1653",
    "shop_name": "زرین شاپ",
    "images": [
        "assets/زنانه/ساعت زنانه/1369284/23f014f77d6f260b0c1acd6883f2fcfa.jpg",
        "assets/زنانه/ساعت زنانه/1369284/177240e3a1bc72b17830e6d4f41199fb.jpg",
        "assets/زنانه/ساعت زنانه/1369284/aba69cc7f3cb770b46831321b9f42d39.jpg",
        "assets/زنانه/ساعت زنانه/1369284/15d0bf553ca46520b2639c21ae8a0c2e.jpg",
        "assets/زنانه/ساعت زنانه/1369284/00f39f568ff6bcbba5b805ac8d899a3d.jpg",
        "assets/زنانه/ساعت زنانه/1369284/23f014f77d6f260b0c1acd6883f2fcfa.jpg",
        "assets/زنانه/ساعت زنانه/1369284/177240e3a1bc72b17830e6d4f41199fb.jpg",
        "assets/زنانه/ساعت زنانه/1369284/aba69cc7f3cb770b46831321b9f42d39.jpg",
        "assets/زنانه/ساعت زنانه/1369284/15d0bf553ca46520b2639c21ae8a0c2e.jpg",
        "assets/زنانه/ساعت زنانه/1369284/00f39f568ff6bcbba5b805ac8d899a3d.jpg",
        "assets/زنانه/ساعت زنانه/1369284/7b90180c9712594e67901f60c68733dc.jpg",
        "assets/زنانه/ساعت زنانه/1369284/7b90180c9712594e67901f60c68733dc.jpg",
        "assets/زنانه/ساعت زنانه/1369284/7b90180c9712594e67901f60c68733dc.jpg"
    ],
    "related_lists": [
        {
            "name": "ساعت زنانه کارتیر مدل سانتوز اکتاگون صفحه سبز ساده زنانه"
        },
        {
            "name": "ساعت دیواری هامون زنانه"
        },
        {
            "name": "ساعت مچی چانگ‌شی زنانه"
        }
    ]
}