{
    "product_id": "1059987",
    "url": "https://shopino.app/product/1059987",
    "main_category": "مردانه",
    "sub_category": "کلاه مردانه",
    "title": "کلاه ماسک جوشکاری دوبین",
    "description": "این کلاه ماسک مخصوص استفاده در جوشکاری و محافظ صورت در برابر سوختگی می باشد",
    "price": "No Price",
    "old_price": null,
    "discount_percentage": null,
    "shop_url": "https://shopino.app/shops/1683",
    "shop_name": "ایمن کارا",
    "images": [
        "assets/مردانه/کلاه مردانه/1059987/594533ac1e90b53f98bb06dceef4fc24.webp",
        "assets/مردانه/کلاه مردانه/1059987/208d7d12c9e599e12bbf71ef5e8c17f6.webp",
        "assets/مردانه/کلاه مردانه/1059987/5cf3c59e6ec3cfe130c40d5d7e452a50.webp",
        "assets/مردانه/کلاه مردانه/1059987/594533ac1e90b53f98bb06dceef4fc24.webp",
        "assets/مردانه/کلاه مردانه/1059987/208d7d12c9e599e12bbf71ef5e8c17f6.webp",
        "assets/مردانه/کلاه مردانه/1059987/5cf3c59e6ec3cfe130c40d5d7e452a50.webp",
        "assets/مردانه/کلاه مردانه/1059987/e520e5faf0d7d0d20ad6a063bda2e6ee.webp",
        "assets/مردانه/کلاه مردانه/1059987/e520e5faf0d7d0d20ad6a063bda2e6ee.webp",
        "assets/مردانه/کلاه مردانه/1059987/e520e5faf0d7d0d20ad6a063bda2e6ee.webp"
    ],
    "related_lists": []
}