{
    "product_id": "715168",
    "url": "https://shopino.app/product/715168",
    "main_category": "مردانه",
    "sub_category": "صندل مردانه",
    "title": "صندل مردانه Adidas",
    "description": null,
    "price": "429,000",
    "old_price": "489,000",
    "discount_percentage": "12 %",
    "shop_url": "https://shopino.app/shops/1577",
    "shop_name": "بکس استور",
    "images": [
        "assets/مردانه/صندل مردانه/715168/cda67fc5cde77f0d5ee11e8b2a16f0f4.jpg",
        "assets/مردانه/صندل مردانه/715168/cda67fc5cde77f0d5ee11e8b2a16f0f4.jpg",
        "assets/مردانه/صندل مردانه/715168/baxstore.ir.webp",
        "assets/مردانه/صندل مردانه/715168/baxstore.ir.webp",
        "assets/مردانه/صندل مردانه/715168/baxstore.ir.webp"
    ],
    "related_lists": [
        {
            "name": "صندل چرم سگک‌کمربندی مردانه"
        },
        {
            "name": "صندل طبی و چرم مردانه"
        },
        {
            "name": "اسلیپر NIKE مردانه"
        }
    ]
}